README.rst
setup.cfg
setup.py
carvajal/__about__.py
carvajal/__init__.py
carvajal/aws.py
carvajal/terraform.py
carvajal/utils.py
carvajal.egg-info/PKG-INFO
carvajal.egg-info/SOURCES.txt
carvajal.egg-info/dependency_links.txt
carvajal.egg-info/requires.txt
carvajal.egg-info/top_level.txt
test/test_aws.py
test/test_utils.py